telometer/__init__.py
telometer/telometer.py
telometer-1.1.dist-info/LICENSE.txt
telometer-1.1.dist-info/METADATA
telometer-1.1.dist-info/WHEEL
telometer-1.1.dist-info/entry_points.txt
telometer-1.1.dist-info/top_level.txt
telometer-1.1.dist-info/RECORD
